LICENSE
README.rst
pyproject.toml
setup.py
BotUtils/CommonUtils.py
BotUtils/__init__.py
BotUtils.egg-info/PKG-INFO
BotUtils.egg-info/SOURCES.txt
BotUtils.egg-info/dependency_links.txt
BotUtils.egg-info/requires.txt
BotUtils.egg-info/top_level.txt