Metadata-Version: 2.1
Name: BotUtils
Version: 2.2.0
Summary: Personal Utilities for Spaz's bots
Home-page: UNKNOWN
Author: Lil_SpazJoekp
Author-email: lilspazjoekp@gmail.com
License: Private
Platform: UNKNOWN
Provides-Extra: tunnel
Provides-Extra: sqla
Provides-Extra: lint
Provides-Extra: dev
License-File: LICENSE
